{
    "progressbar-animation-ease-in-out-indeterminate": {
        "component": "progress-bar",
        "$schema": "https://opensource.adobe.com/spectrum-tokens/schemas/token-types/alias.json",
        "value": "{animation-ease-in-out}"
    },
    "progressbar-animation-duration-indeterminate": {
        "component": "progress-bar",
        "$schema": "https://opensource.adobe.com/spectrum-tokens/schemas/token-types/alias.json",
        "value": "{animation-duration-2000}"
    },
    "progressbar-corner-radius": {
        "component": "progress-bar",
        "$schema": "https://opensource.adobe.com/spectrum-tokens/schemas/token-types/alias.json",
        "value": "{corner-radius-full}"
    },
    "progressbar-fill-size-indeterminate": {
        "component": "progress-bar",
        "$schema": "https://opensource.adobe.com/spectrum-tokens/schemas/token-types/dimension.json",
        "value": "70%"
    },
    "progressbar-size-2400": {
        "component": "progress-bar",
        "$schema": "https://opensource.adobe.com/spectrum-tokens/schemas/token-types/dimension.json",
        "value": "192px"
    },
    "progressbar-size-2500": {
        "component": "progress-bar",
        "$schema": "https://opensource.adobe.com/spectrum-tokens/schemas/token-types/dimension.json",
        "value": "200px"
    },
    "progressbar-size-2800": {
        "component": "progress-bar",
        "$schema": "https://opensource.adobe.com/spectrum-tokens/schemas/token-types/dimension.json",
        "value": "224px"
    },
    "progressbar-size-default": {
        "component": "progress-bar",
        "$schema": "https://opensource.adobe.com/spectrum-tokens/schemas/token-types/alias.json",
        "value": "{progressbar-size-2400}"
    },
    "progressbar-font-size": {
        "component": "progress-bar",
        "$schema": "https://opensource.adobe.com/spectrum-tokens/schemas/token-types/alias.json",
        "value": "{font-size-100}"
    },
    "progressbar-line-height": {
        "component": "progress-bar",
        "$schema": "https://opensource.adobe.com/spectrum-tokens/schemas/token-types/alias.json",
        "value": "{line-height-100}"
    },
    "progressbar-line-height-cjk": {
        "component": "progress-bar",
        "$schema": "https://opensource.adobe.com/spectrum-tokens/schemas/token-types/alias.json",
        "value": "{cjk-line-height-100}"
    },
    "progressbar-min-size": {
        "component": "progress-bar",
        "$schema": "https://opensource.adobe.com/spectrum-tokens/schemas/token-types/alias.json",
        "value": "{progress-bar-minimum-width}"
    },
    "progressbar-max-size": {
        "component": "progress-bar",
        "$schema": "https://opensource.adobe.com/spectrum-tokens/schemas/token-types/alias.json",
        "value": "{progress-bar-maximum-width}"
    },
    "progressbar-thickness": {
        "component": "progress-bar",
        "$schema": "https://opensource.adobe.com/spectrum-tokens/schemas/token-types/alias.json",
        "value": "{progress-bar-thickness-medium}"
    },
    "progressbar-spacing-label-to-progressbar": {
        "component": "progress-bar",
        "$schema": "https://opensource.adobe.com/spectrum-tokens/schemas/token-types/alias.json",
        "value": "{spacing-75}"
    },
    "progressbar-spacing-top-to-text": {
        "component": "progress-bar",
        "$schema": "https://opensource.adobe.com/spectrum-tokens/schemas/token-types/alias.json",
        "value": "{component-top-to-text-100}"
    },
    "progressbar-spacing-label-to-text": {
        "component": "progress-bar",
        "$schema": "https://opensource.adobe.com/spectrum-tokens/schemas/token-types/alias.json",
        "value": "{spacing-200}"
    },
    "progressbar-text-color": {
        "component": "progress-bar",
        "$schema": "https://opensource.adobe.com/spectrum-tokens/schemas/token-types/alias.json",
        "value": "{neutral-subdued-content-color-default}"
    },
    "progressbar-track-color": {
        "component": "progress-bar",
        "$schema": "https://opensource.adobe.com/spectrum-tokens/schemas/token-types/alias.json",
        "value": "{gray-300}",
        "sets": {
            "whcm": {
                "$schema": "https://opensource.adobe.com/spectrum-tokens/schemas/token-types/color.json",
                "value": "ButtonFace"
            }
        }
    },
    "progressbar-fill-color": {
        "component": "progress-bar",
        "$schema": "https://opensource.adobe.com/spectrum-tokens/schemas/token-types/alias.json",
        "value": "{accent-content-color-default}",
        "sets": {
            "whcm": {
                "$schema": "https://opensource.adobe.com/spectrum-tokens/schemas/token-types/color.json",
                "value": "ButtonText"
            }
        }
    },
    "progressbar-label-and-value-white": {
        "component": "progress-bar",
        "$schema": "https://opensource.adobe.com/spectrum-tokens/schemas/token-types/alias.json",
        "value": "{transparent-white-700}"
    },
    "progressbar-track-color-white": {
        "component": "progress-bar",
        "$schema": "https://opensource.adobe.com/spectrum-tokens/schemas/token-types/alias.json",
        "value": "{transparent-white-300}"
    },
    "progressbar-fill-color-white": {
        "component": "progress-bar",
        "$schema": "https://opensource.adobe.com/spectrum-tokens/schemas/token-types/alias.json",
        "value": "{transparent-white-900}",
        "sets": {
            "whcm": {
                "$schema": "https://opensource.adobe.com/spectrum-tokens/schemas/token-types/color.json",
                "value": "ButtonText"
            }
        }
    }
}
