{"menu":[{"title":"WebsiteMenu","url":"header-WebsiteMenu","linkType":"group","parent":"top-level-menu-item","children":[{"title":"Components","url":"header-Components","linkType":"group","parent":"top-level-menu-item,WebsiteMenu","children":[{"title":"Bar Loader","url":"barloader","linkType":"Internal","parent":"top-level-menu-item,WebsiteMenu,Components"},{"title":"Checkbox","url":"checkbox","linkType":"Internal","parent":"top-level-menu-item,WebsiteMenu,Components"}]}]}],"key":[{"title":"WebsiteMenu","url":"header-WebsiteMenu","linkType":"group","parent":"top-level-menu-item"},{"title":"Components","url":"header-Components","linkType":"group","parent":"top-level-menu-item,WebsiteMenu"},{"title":"Bar Loader","url":"barloader","linkType":"Internal","parent":"top-level-menu-item,WebsiteMenu,Components"},{"title":"Checkbox","url":"checkbox","linkType":"Internal","parent":"top-level-menu-item,WebsiteMenu,Components"}]}